js_go/__init__.py
js_go/constants.py
js_go/function.py
js_go/go_game.py
js_go/go_logic.py
js_go-0.1.4.dist-info/METADATA
js_go-0.1.4.dist-info/WHEEL
js_go-0.1.4.dist-info/top_level.txt
js_go-0.1.4.dist-info/RECORD
